pnu_what-1.0.0.data/data/man/man1/what.1.gz
what/__init__.py
what/main.py
pnu_what-1.0.0.dist-info/License
pnu_what-1.0.0.dist-info/METADATA
pnu_what-1.0.0.dist-info/WHEEL
pnu_what-1.0.0.dist-info/entry_points.txt
pnu_what-1.0.0.dist-info/top_level.txt
pnu_what-1.0.0.dist-info/RECORD
